ai_aside/__init__.py
ai_aside/apps.py
ai_aside/block.py
ai_aside/constants.py
ai_aside/models.py
ai_aside/platform_imports.py
ai_aside/plugins.py
ai_aside/plugins_api.py
ai_aside/text_utils.py
ai_aside/urls.py
ai_aside/waffle.py
ai_aside/config_api/__init__.py
ai_aside/config_api/api.py
ai_aside/config_api/exceptions.py
ai_aside/config_api/internal.py
ai_aside/config_api/permissions.py
ai_aside/config_api/urls.py
ai_aside/config_api/validators.py
ai_aside/config_api/view_utils.py
ai_aside/config_api/views.py
ai_aside/migrations/0001_initial.py
ai_aside/migrations/0002_auto_20230720_1544.py
ai_aside/migrations/__init__.py
ai_aside/settings/__init__.py
ai_aside/settings/common.py
ai_aside/settings/devstack.py
ai_aside/settings/production.py
ai_aside-3.8.2.dist-info/LICENSE.txt
ai_aside-3.8.2.dist-info/METADATA
ai_aside-3.8.2.dist-info/WHEEL
ai_aside-3.8.2.dist-info/entry_points.txt
ai_aside-3.8.2.dist-info/top_level.txt
ai_aside-3.8.2.dist-info/RECORD
