Metadata-Version: 2.1
Name: ai-aside
Version: 3.8.2
Summary: A plugin containing xblocks and apps supporting GPT and other LLM use on edX.
Home-page: https://github.com/openedx/ai-aside
Author: edX
Author-email: ashultz@edx.org
License: AGPL 3.0
Keywords: Python edx
Classifier: Development Status :: 3 - Alpha
Classifier: Framework :: Django
Classifier: Framework :: Django :: 3.2
Classifier: Intended Audience :: Developers
Classifier: License :: OSI Approved :: GNU Affero General Public License v3 or later (AGPLv3+)
Classifier: Natural Language :: English
Classifier: Programming Language :: Python :: 3
Classifier: Programming Language :: Python :: 3.8
Requires-Python: >=3.8
License-File: LICENSE.txt
Requires-Dist: Django
Requires-Dist: djangorestframework
Requires-Dist: edx-drf-extensions
Requires-Dist: edx-opaque-keys
Requires-Dist: edx-django-utils
Requires-Dist: xblock
